qoqo_qiskit_devices-0.10.1.dist-info/METADATA
qoqo_qiskit_devices-0.10.1.dist-info/WHEEL
qoqo_qiskit_devices-0.10.1.dist-info/licenses/LICENSE
qoqo_qiskit_devices/DEPENDENCIES
qoqo_qiskit_devices/__init__.py
qoqo_qiskit_devices/device_property.py
qoqo_qiskit_devices/PYTHON_LICENSE
qoqo_qiskit_devices/LICENSE_FOR_BINARY_DISTRIBUTION
qoqo_qiskit_devices/mocked_properties.py
qoqo_qiskit_devices/qoqo_qiskit_devices.cpython-312-darwin.so
qoqo_qiskit_devices-0.10.1.dist-info/RECORD
