Metadata-Version: 2.4
Name: qoqo_qiskit_devices
Version: 0.10.1
Requires-Dist: qoqo-calculator-pyo3>=1.5,<1.6
Requires-Dist: qoqo>=1.19,<1.20
Requires-Dist: qiskit>=1.0,<1.3
Requires-Dist: qiskit-ibm-runtime>=0.35,<0.36
Requires-Dist: struqture-py
Requires-Dist: setuptools ; python_full_version >= '3.12'
Requires-Dist: numpy ; extra == 'docs'
Requires-Dist: sphinx>=2.1 ; extra == 'docs'
Requires-Dist: nbsphinx ; extra == 'docs'
Requires-Dist: pygments ; extra == 'docs'
Requires-Dist: recommonmark ; extra == 'docs'
Requires-Dist: myst-parser ; extra == 'docs'
Requires-Dist: sphinx-rtd-theme ; extra == 'docs'
Requires-Dist: tomli ; extra == 'docs'
Provides-Extra: docs
License-File: LICENSE
Summary: IBM's Qiskit devices interface for qoqo python quantum computing toolkit
Author: HQS Quantum Simulations <info@quantumsimulations.de>
Author-email: HQS Quantum Simulations <info@quantumsimulations.de>
Maintainer-email: HQS Quantum Simulations GmbH <info@quantumsimulations.de>
License: Apache-2.0 AND Apache-2.0 with LLVM-exception AND MIT AND Unicode-DFS-2016 AND
Requires-Python: >=3.9
Project-URL: Source Code, https://github.com/HQSquantumsimulations/qoqo_qiskit
